cli/dedupe.py
cli/entrypoint.py
core/actions.py
core/comperator.py
core/hasher.py
core/log.py
core/output.py
core/scanner.py
deduplicate_cli-1.2.8.dist-info/licenses/LICENSE
ui/adapter_actions.py
ui/adapter_comperator.py
ui/adapter_hasher.py
ui/adapter_output.py
ui/adapter_scanner.py
ui/display.py
ui/verbose.py
deduplicate_cli-1.2.8.dist-info/METADATA
deduplicate_cli-1.2.8.dist-info/WHEEL
deduplicate_cli-1.2.8.dist-info/entry_points.txt
deduplicate_cli-1.2.8.dist-info/top_level.txt
deduplicate_cli-1.2.8.dist-info/RECORD
