Metadata-Version: 2.4
Name: deduplicate-cli
Version: 1.2.8
Summary: A fast CLI tool to find and manage duplicate files.
Author-email: Ibby <ibrahimissa00@proton.me>
License: MIT
Project-URL: Homepage, https://github.com/IbbyI/deduplicate
Project-URL: Source, https://github.com/IbbyI/deduplicate
Project-URL: Issues, https://github.com/IbbyI/deduplicate/issues
Requires-Python: >=3.10
License-File: LICENSE
Requires-Dist: rich
Requires-Dist: tabulate
Dynamic: license-file
